yafowil.widget.location-1.3-py3.9-nspkg.pth
yafowil/widget/location/__init__.py
yafowil/widget/location/example.py
yafowil/widget/location/tests.py
yafowil/widget/location/widget.py
yafowil/widget/location/resources/widget.css
yafowil/widget/location/resources/widget.js
yafowil/widget/location/resources/L.GeoSearch/l.control.geosearch.js
yafowil/widget/location/resources/L.GeoSearch/l.geosearch.css
yafowil/widget/location/resources/L.GeoSearch/l.geosearch.provider.bing.js
yafowil/widget/location/resources/L.GeoSearch/l.geosearch.provider.esri.js
yafowil/widget/location/resources/L.GeoSearch/l.geosearch.provider.google.js
yafowil/widget/location/resources/L.GeoSearch/l.geosearch.provider.nokia.js
yafowil/widget/location/resources/L.GeoSearch/l.geosearch.provider.openstreetmap.js
yafowil/widget/location/resources/Leaflet/leaflet-src.js
yafowil/widget/location/resources/Leaflet/leaflet.css
yafowil/widget/location/resources/Leaflet/leaflet.js
yafowil/widget/location/resources/Leaflet/images/layers-2x.png
yafowil/widget/location/resources/Leaflet/images/layers.png
yafowil/widget/location/resources/Leaflet/images/marker-icon-2x.png
yafowil/widget/location/resources/Leaflet/images/marker-icon.png
yafowil/widget/location/resources/Leaflet/images/marker-shadow.png
yafowil_widget_location-1.3.dist-info/licenses/LICENSE.rst
yafowil_widget_location-1.3.dist-info/METADATA
yafowil_widget_location-1.3.dist-info/WHEEL
yafowil_widget_location-1.3.dist-info/entry_points.txt
yafowil_widget_location-1.3.dist-info/namespace_packages.txt
yafowil_widget_location-1.3.dist-info/top_level.txt
yafowil_widget_location-1.3.dist-info/RECORD
